LICENSE
MANIFEST.in
README.md
setup.py
django_ember_index.egg-info/PKG-INFO
django_ember_index.egg-info/SOURCES.txt
django_ember_index.egg-info/dependency_links.txt
django_ember_index.egg-info/top_level.txt
ember_index/__init__.py
ember_index/utils.py
ember_index/views.py